<?xml version="1.0" encoding="UTF-8"?>
<SlimOTA xmlns:xsi="http://www.w3.org/2001/XMLSchema-instance" xsi:noNamespaceSchemaLocation="ota.xsd">
    <Stable>
        <oneplus3>
            <Filename>aicp_oneplus3_n-12.1-mordiford-20170217_144526.zip</Filename>
            <RomUrl
                id="rom"
                title="ROM"
                description="Download AICP-mordiford for OnePlus 3 (oneplus3)">https://drive.google.com/drive/folders/0ByoQOmqDxjD7bXlOX0NSU1VaMVU</RomUrl>
            <ReadmeUrl
                id="readme"
                title="README"
                description="View README">https://github.com/mordiford/IceManifests/wiki</ReadmeUrl>
        </oneplus3>
    </Stable>
</SlimOTA>
